Metadata-Version: 1.2
Name: histog
Version: 0.1.0
Summary: Draw histogram based on a set of integers from STDIN.
Home-page: https://github.com/nul-one/histog
Author: Predrag Mandic
Author-email: info@nul.one
License: BSD
Download-URL: https://github.com/nul-one/histog/archive/0.1.0.tar.gz
Platform: UNKNOWN
Requires-Python: >=3.4.6
